starlette_request_id/__init__.py
starlette_request_id/constants.py
starlette_request_id/middleware.py
starlette_request_id/version.py
tests/__init__.py
tests/conftest.py
tests/test_helper.py
tests/test_middleware.py
starlette_request_id-1.2.1.dist-info/LICENSE
starlette_request_id-1.2.1.dist-info/METADATA
starlette_request_id-1.2.1.dist-info/WHEEL
starlette_request_id-1.2.1.dist-info/top_level.txt
starlette_request_id-1.2.1.dist-info/RECORD
